pyaudioclassification/__init__.py
pyaudioclassification/feat_extract.py
pyaudioclassification/models.py
pyaudioclassification-0.1.9.data/scripts/feature_extraction
pyaudioclassification-0.1.9.dist-info/LICENSE
pyaudioclassification-0.1.9.dist-info/METADATA
pyaudioclassification-0.1.9.dist-info/WHEEL
pyaudioclassification-0.1.9.dist-info/top_level.txt
pyaudioclassification-0.1.9.dist-info/RECORD
