Metadata-Version: 2.1
Name: pyaudioclassification
Version: 0.1.9
Summary: Dead simple audio classification
Home-page: https://github.com/98mprice/pyAudioClassification
Author: 98mprice
Author-email: 98mprice@gmail.com
License: MIT
Keywords: simple audio classification
Platform: UNKNOWN
Classifier: Development Status :: 3 - Alpha
Classifier: License :: OSI Approved :: MIT License
Classifier: Programming Language :: Python :: 2.7
Requires-Dist: numpy
Requires-Dist: librosa
Requires-Dist: soundfile
Requires-Dist: tqdm
Requires-Dist: keras
